README.rst
setup.py
zlgp/__init__.py
zlgp/api.py
zlgp/task.py
zlgp.egg-info/PKG-INFO
zlgp.egg-info/SOURCES.txt
zlgp.egg-info/dependency_links.txt
zlgp.egg-info/requires.txt
zlgp.egg-info/top_level.txt
zlgp/dst/__init__.py
zlgp/dst/api.py
zlgp/dst/core.py
zlgp/dst/union.py
zlgp/dst/algo/__init__.py
zlgp/dst/algo/api.py
zlgp/dst/algo/core.py
zlgp/dst/bid/__init__.py
zlgp/dst/bid/api.py
zlgp/dst/bid/core.py
zlgp/dst/bid_bridge/__init__.py
zlgp/dst/bid_bridge/api.py
zlgp/dst/bid_bridge/core.py
zlgp/dst/page/__init__.py
zlgp/dst/page/api.py
zlgp/dst/page/core.py
zlgp/src/__init__.py
zlgp/src/api.py
zlgp/src/core.py